glair/__init__.py
glair/main.py
glair/model.py
glair/processing.py
glair-1.1.dist-info/METADATA
glair-1.1.dist-info/WHEEL
glair-1.1.dist-info/top_level.txt
glair-1.1.dist-info/RECORD
